CHANGELOG.md
LICENSE
README.md
roboai_cli/__init__.py
roboai_cli/__main__.py
roboai_cli/commands/__init__.py
roboai_cli/commands/clean.py
roboai_cli/commands/connect.py
roboai_cli/commands/data.py
roboai_cli/commands/deploy.py
roboai_cli/commands/diff.py
roboai_cli/commands/environment.py
roboai_cli/commands/interactive.py
roboai_cli/commands/login.py
roboai_cli/commands/logout.py
roboai_cli/commands/logs.py
roboai_cli/commands/package.py
roboai_cli/commands/remove.py
roboai_cli/commands/run.py
roboai_cli/commands/seed.py
roboai_cli/commands/shell.py
roboai_cli/commands/start.py
roboai_cli/commands/status.py
roboai_cli/commands/stop.py
roboai_cli/commands/stories.py
roboai_cli/commands/test.py
roboai_cli/commands/train.py
roboai_cli/config/__init__.py
roboai_cli/config/bot_manifest.py
roboai_cli/config/environment_constants.py
roboai_cli/config/environment_settings.py
roboai_cli/config/store/__init__.py
roboai_cli/config/store/utils.py
roboai_cli/config/tool_settings.py
roboai_cli/initial_structure/initial_project/.botignore
roboai_cli/initial_structure/initial_project/__init__.py
roboai_cli/initial_structure/initial_project/actions/action.py
roboai_cli/initial_structure/initial_project/actions/action_parlai_fallback.py
roboai_cli/initial_structure/initial_project/credentials.yml
roboai_cli/initial_structure/initial_project/custom/components/exact_match_classifier/exact_match_classifier.py
roboai_cli/initial_structure/initial_project/custom/components/spacy_nlp/spacy_nlp_neuralcoref.py
roboai_cli/initial_structure/initial_project/custom/components/spacy_nlp/spacy_tokenizer_neuralcoref.py
roboai_cli/initial_structure/initial_project/custom/policies/language_detection/lang_change_policy.py
roboai_cli/initial_structure/initial_project/custom/policies/language_detection/lid.176.ftz
roboai_cli/initial_structure/initial_project/endpoints.yml
roboai_cli/initial_structure/initial_project/languages/stories.md
roboai_cli/initial_structure/initial_project/requirements.txt
roboai_cli-1.1.2.dist-info/entry_points.txt
roboai_cli-1.1.2.dist-info/LICENSE
roboai_cli-1.1.2.dist-info/WHEEL
roboai_cli-1.1.2.dist-info/METADATA
roboai_cli-1.1.2.dist-info/RECORD
