Metadata-Version: 2.1
Name: roboai-cli
Version: 1.1.2
Summary: A command line tool to create, manage and deploy Rasa chatbots on the Robo.AI platform.
Home-page: https://robo-ai.com/
License: MIT
Keywords: rasa chatbot manager
Author: ROBO.AI
Author-email: info@robo-ai.com
Requires-Python: >=3.7,<3.8
Classifier: License :: OSI Approved :: MIT License
Classifier: Operating System :: OS Independent
Classifier: Programming Language :: Python :: 3
Classifier: Programming Language :: Python :: 3.7
Requires-Dist: Pygments (==2.6.1)
Requires-Dist: XlsxWriter (==1.3.7)
Requires-Dist: attrs (==19.3.0)
Requires-Dist: cattrs (==1.0.0)
Requires-Dist: certifi (==2020.4.5.1)
Requires-Dist: chardet (==3.0.4)
Requires-Dist: click (==7.1.2)
Requires-Dist: colorama (==0.4.3)
Requires-Dist: cursor (==1.3.4)
Requires-Dist: halo (==0.0.29)
Requires-Dist: idna (==2.9)
Requires-Dist: log-symbols (==0.0.14)
Requires-Dist: openpyxl (==3.0.4)
Requires-Dist: pandas (==1.0.5)
Requires-Dist: polling (==0.3.1)
Requires-Dist: pyfiglet (==0.8.post1)
Requires-Dist: pytablewriter (==0.57.0)
Requires-Dist: questionary (==1.5.2)
Requires-Dist: rasa (==1.10.0)
Requires-Dist: regex (==2020.5.14)
Requires-Dist: requests (==2.23.0)
Requires-Dist: robo_ai (>=0.1.1,<0.2.0)
Requires-Dist: six (==1.14.0)
Requires-Dist: spinners (==0.0.24)
Requires-Dist: termcolor (==1.1.0)
Requires-Dist: urllib3 (==1.25.9)
Requires-Dist: wcwidth (==0.1.9)
Project-URL: Repository, https://github.com/robo-ai/roboai-python-cli
